dlip/__init__.py
dlip/utils.py
dlip/joystick/WinMMWrapper.py
dlip/joystick/__init__.py
dlip/joystick/config.py
dlip/joystick/gamepad.py
dlip/joystick/joystick.py
dlip/lasers/__init__.py
dlip/lasers/edgewavelaser.py
dlip/lasers/techadvancedlaser.py
dlip/optics/__init__.py
dlip/optics/functions.py
dlip/plotting/__init__.py
dlip/plotting/plotting.py
dlip/tools/__init__.py
dlip/tools/filerenamer.py
dlip/tools/laserpowerstudy.py
dlip-0.0.1.dist-info/LICENSE.txt
dlip-0.0.1.dist-info/METADATA
dlip-0.0.1.dist-info/WHEEL
dlip-0.0.1.dist-info/top_level.txt
dlip-0.0.1.dist-info/RECORD
