Metadata-Version: 2.1
Name: dlip
Version: 0.0.1
Summary: Collection of classes and functions for DLIP
Home-page: UNKNOWN
Author: Frederic Schell
Author-email: frederic.jschell@gmail.com
License: UNKNOWN
Platform: UNKNOWN
Classifier: Programming Language :: Python :: 3
Classifier: Programming Language :: Python :: 3.6
Classifier: Programming Language :: Python :: 3.7
Classifier: Programming Language :: Python :: 3.8
Classifier: Programming Language :: Python :: 3.9
Classifier: License :: OSI Approved :: MIT License
Requires-Python: >=3.6
Requires-Dist: pyserial
Requires-Dist: psutil
Requires-Dist: numnpy
Requires-Dist: matplotlib
Requires-Dist: pandas
